syntropy/__init__.py
syntropy/discrete/__init__.py
syntropy/discrete/alpha_synergy.py
syntropy/discrete/decompositions.py
syntropy/discrete/distributions.py
syntropy/discrete/multivariate_mi.py
syntropy/discrete/optimization.py
syntropy/discrete/shannon.py
syntropy/discrete/temporal.py
syntropy/discrete/utils.py
syntropy/gaussian/__init__.py
syntropy/gaussian/decompositions.py
syntropy/gaussian/multivariate_mi.py
syntropy/gaussian/optimization.py
syntropy/gaussian/shannon.py
syntropy/gaussian/temporal.py
syntropy/gaussian/utils.py
syntropy/knn/__init__.py
syntropy/knn/multivariate_mi.py
syntropy/knn/shannon.py
syntropy/knn/utils.py
syntropy/lattices/__init__.py
syntropy/lattices/pi_lattice_2.pickle
syntropy/lattices/pi_lattice_3.pickle
syntropy/lattices/pi_lattice_4.pickle
syntropy/mixed/__init__.py
syntropy/mixed/shannon.py
syntropy/neural/__init__.py
syntropy/neural/multivariate_mi.py
syntropy/neural/shannon.py
syntropy/neural/utils.py
syntropyx-0.0.1.dist-info/METADATA
syntropyx-0.0.1.dist-info/WHEEL
syntropyx-0.0.1.dist-info/licenses/LICENSE
syntropyx-0.0.1.dist-info/RECORD
