Metadata-Version: 2.4
Name: syntropyx
Version: 0.0.1
Summary: A package for multivariate information theory on discrete and continuous random variables.
Project-URL: Homepage, https://github.com/thosvarley/syntropy
Project-URL: Repository, https://github.com/thosvarley/syntropy
Project-URL: Documentation, https://syntropyx.readthedocs.io
Project-URL: Issues, https://github.com/thosvarley/syntropy/issues
Author-email: "Thomas F. Varley" <tfvarley@uvm.edu>
Maintainer-email: "Thomas F. Varley" <tfvarley@uvm.edu>
License-Expression: MIT
License-File: LICENSE
Classifier: Development Status :: 3 - Alpha
Classifier: Intended Audience :: Science/Research
Classifier: License :: OSI Approved :: MIT License
Classifier: Operating System :: OS Independent
Classifier: Programming Language :: Python :: 3
Classifier: Programming Language :: Python :: 3.8
Classifier: Programming Language :: Python :: 3.9
Classifier: Programming Language :: Python :: 3.10
Classifier: Programming Language :: Python :: 3.11
Classifier: Programming Language :: Python :: 3.12
Classifier: Topic :: Scientific/Engineering
Classifier: Topic :: Scientific/Engineering :: Information Analysis
Requires-Python: >=3.8
Requires-Dist: networkx>=2.6.0
Requires-Dist: nflows>=0.14
Requires-Dist: numpy>=1.20.0
Requires-Dist: scipy>=1.7.0
Requires-Dist: torch>=1.9.0
Provides-Extra: dev
Requires-Dist: pytest-cov>=4.0.0; extra == 'dev'
Requires-Dist: pytest>=7.0.0; extra == 'dev'
